{
	"configurations" : 
	[
		{
			"directories" : 
			[
				{
					"build" : ".",
					"jsonFile" : "directory-.-Debug-d0094a50bb2071803777.json",
					"minimumCMakeVersion" : 
					{
						"string" : "3.29"
					},
					"projectIndex" : 0,
					"source" : ".",
					"targetIndexes" : 
					[
						0
					]
				}
			],
			"name" : "Debug",
			"projects" : 
			[
				{
					"directoryIndexes" : 
					[
						0
					],
					"name" : "example2",
					"targetIndexes" : 
					[
						0
					]
				}
			],
			"targets" : 
			[
				{
					"directoryIndex" : 0,
					"id" : "example2::@6890427a1f51a3e7e1df",
					"jsonFile" : "target-example2-Debug-9b883ea09b6ca12d8a6b.json",
					"name" : "example2",
					"projectIndex" : 0
				}
			]
		}
	],
	"kind" : "codemodel",
	"paths" : 
	{
		"build" : "E:/Workspace/Cpp/DSA/shirafkan/03-stack/example2/cmake-build-debug",
		"source" : "E:/Workspace/Cpp/DSA/shirafkan/03-stack/example2"
	},
	"version" : 
	{
		"major" : 2,
		"minor" : 7
	}
}
